ximu3csv/__init__.py
ximu3csv/convert_to_euler_angles.py
ximu3csv/crop.py
ximu3csv/data_messages.py
ximu3csv/device.py
ximu3csv/read.py
ximu3csv/resample.py
ximu3csv/zero_first_timestamp.py
ximu3csv/zero_heading.py
ximu3csv-1.0.3.dist-info/licenses/LICENSE.md
ximu3csv-1.0.3.dist-info/METADATA
ximu3csv-1.0.3.dist-info/WHEEL
ximu3csv-1.0.3.dist-info/top_level.txt
ximu3csv-1.0.3.dist-info/RECORD
