Metadata-Version: 2.4
Name: ximu3csv
Version: 1.0.3
Summary: x-IMU3 CSV
Author-email: x-io Technologies Limited <info@x-io.co.uk>
License: 
Project-URL: Repository, https://github.com/xioTechnologies/x-IMU3-CSV
License-File: LICENSE.md
Dynamic: license-file
